[1,["99iWWZbjdIq7lYZBYk2Z5b@6c48a"],["_textureSource"],["cc.SpriteFrame"],0,[{"name":"hit_0_1","rect":{"x":8,"y":17,"width":31,"height":50},"offset":{"x":-7,"y":-1},"originalSize":{"width":61,"height":82},"rotated":false,"capInsets":[0,0,0,0],"vertices":{"rawPosition":[-15.5,-25,0,15.5,-25,0,-15.5,25,0,15.5,25,0],"indexes":[0,1,2,2,1,3],"uv":[8,65,39,65,8,15,39,15],"nuv":[0.13114754098360656,0.18292682926829268,0.639344262295082,0.18292682926829268,0.13114754098360656,0.7926829268292683,0.639344262295082,0.7926829268292683],"minPos":{"x":-15.5,"y":-25,"z":0},"maxPos":{"x":15.5,"y":25,"z":0}},"packable":true,"pixelsToUnit":100,"pivot":{"x":0.5,"y":0.5},"meshType":0}],[0],0,[0],[0],[0]]
