[1,0,0,[["cc.JsonAsset",["_name","json"],1]],[[0,0,1,3]],[[0,"motion",{"frameRate":12,"die":{"frames":[{"res":"z_108","x":326,"y":331}]},"hit":{"frames":[{"res":"z_107","x":307,"y":274}]},"attack":{"frames":[{"res":"z_105","x":328,"y":258},{"res":"z_106","x":329,"y":257},{"res":"z_101","x":329,"y":254},{"res":"z_102","x":317,"y":265},{"res":"z_103","x":318,"y":273},{"res":"z_104","x":316,"y":272},{"res":"z_109","x":315,"y":269},{"res":"z_110","x":320,"y":264}]},"stand":{"frames":[{"res":"z_202","x":328,"y":258},{"res":"z_203","x":328,"y":257},{"res":"z_204","x":327,"y":257},{"res":"z_201","x":326,"y":257},{"res":"z_207","x":326,"y":257},{"res":"z_208","x":326,"y":257},{"res":"z_205","x":327,"y":257},{"res":"z_206","x":327,"y":258}]}}]],0,0,[],[],[]]
