[1,0,0,[["cc.JsonAsset",["_name","json"],1]],[[0,0,1,3]],[[0,"motion",{"frameRate":12,"die":{"frames":[{"res":"z_103","x":334,"y":357}]},"hit":{"frames":[{"res":"z_101","x":332,"y":295}]},"attack":{"frames":[{"res":"z_110","x":357,"y":291},{"res":"z_107","x":353,"y":291},{"res":"z_106","x":353,"y":290},{"res":"z_109","x":354,"y":290},{"res":"z_108","x":352,"y":289},{"res":"z_105","x":354,"y":290},{"res":"z_104","x":355,"y":289},{"res":"z_102","x":356,"y":289}]},"stand":{"frames":[{"res":"z_205","x":348,"y":293},{"res":"z_204","x":347,"y":292},{"res":"z_203","x":347,"y":292},{"res":"z_202","x":347,"y":291},{"res":"z_201","x":346,"y":290},{"res":"z_207","x":347,"y":291},{"res":"z_206","x":348,"y":291},{"res":"z_208","x":347,"y":292}]}}]],0,0,[],[],[]]
