[1,["e9nN5jXd5MY7bzCltPr3aG@6c48a"],["_textureSource"],["cc.SpriteFrame"],0,[{"name":"b_105","rect":{"x":8,"y":2,"width":382,"height":306},"offset":{"x":3,"y":-1},"originalSize":{"width":392,"height":308},"rotated":false,"capInsets":[0,0,0,0],"vertices":{"rawPosition":[-191,-153,0,191,-153,0,-191,153,0,191,153,0],"indexes":[0,1,2,2,1,3],"uv":[8,306,390,306,8,0,390,0],"nuv":[0.02040816326530612,0,0.9948979591836735,0,0.02040816326530612,0.9935064935064936,0.9948979591836735,0.9935064935064936],"minPos":{"x":-191,"y":-153,"z":0},"maxPos":{"x":191,"y":153,"z":0}},"packable":true,"pixelsToUnit":100,"pivot":{"x":0.5,"y":0.5},"meshType":0}],[0],0,[0],[0],[0]]
