[1,["21ZppeQGRMDr+ypB0k2L6V@6c48a"],["_textureSource"],["cc.SpriteFrame"],0,[{"name":"b_203","rect":{"x":2,"y":2,"width":91,"height":136},"offset":{"x":-1,"y":1},"originalSize":{"width":97,"height":142},"rotated":false,"capInsets":[0,0,0,0],"vertices":{"rawPosition":[-45.5,-68,0,45.5,-68,0,-45.5,68,0,45.5,68,0],"indexes":[0,1,2,2,1,3],"uv":[2,140,93,140,2,4,93,4],"nuv":[0.020618556701030927,0.028169014084507043,0.9587628865979382,0.028169014084507043,0.020618556701030927,0.9859154929577465,0.9587628865979382,0.9859154929577465],"minPos":{"x":-45.5,"y":-68,"z":0},"maxPos":{"x":45.5,"y":68,"z":0}},"packable":true,"pixelsToUnit":100,"pivot":{"x":0.5,"y":0.5},"meshType":0}],[0],0,[0],[0],[0]]
