[1,["e1Igt2MllCQa9wWjw1FYl8@6c48a"],["_textureSource"],["cc.SpriteFrame"],0,[{"name":"z_104","rect":{"x":1,"y":2,"width":189,"height":93},"offset":{"x":0,"y":-1},"originalSize":{"width":191,"height":95},"rotated":false,"capInsets":[0,0,0,0],"vertices":{"rawPosition":[-94.5,-46.5,0,94.5,-46.5,0,-94.5,46.5,0,94.5,46.5,0],"indexes":[0,1,2,2,1,3],"uv":[1,93,190,93,1,0,190,0],"nuv":[0.005235602094240838,0,0.9947643979057592,0,0.005235602094240838,0.9789473684210527,0.9947643979057592,0.9789473684210527],"minPos":{"x":-94.5,"y":-46.5,"z":0},"maxPos":{"x":94.5,"y":46.5,"z":0}},"packable":true,"pixelsToUnit":100,"pivot":{"x":0.5,"y":0.5},"meshType":0}],[0],0,[0],[0],[0]]
