[1,["88Q6f91fVLW6NKbaiWWiUU@6c48a"],["_textureSource"],["cc.SpriteFrame"],0,[{"name":"z_104","rect":{"x":3,"y":5,"width":67,"height":117},"offset":{"x":0,"y":-0.5},"originalSize":{"width":73,"height":126},"rotated":false,"capInsets":[0,0,0,0],"vertices":{"rawPosition":[-33.5,-58.5,0,33.5,-58.5,0,-33.5,58.5,0,33.5,58.5,0],"indexes":[0,1,2,2,1,3],"uv":[3,121,70,121,3,4,70,4],"nuv":[0.0410958904109589,0.031746031746031744,0.958904109589041,0.031746031746031744,0.0410958904109589,0.9603174603174603,0.958904109589041,0.9603174603174603],"minPos":{"x":-33.5,"y":-58.5,"z":0},"maxPos":{"x":33.5,"y":58.5,"z":0}},"packable":true,"pixelsToUnit":100,"pivot":{"x":0.5,"y":0.5},"meshType":0}],[0],0,[0],[0],[0]]
