[1,["25hG1FXAdGGL/rwvem50nh@6c48a"],["_textureSource"],["cc.SpriteFrame"],0,[{"name":"die_0_0","rect":{"x":5,"y":10,"width":92,"height":38},"offset":{"x":-2.5,"y":0},"originalSize":{"width":107,"height":58},"rotated":false,"capInsets":[0,0,0,0],"vertices":{"rawPosition":[-46,-19,0,46,-19,0,-46,19,0,46,19,0],"indexes":[0,1,2,2,1,3],"uv":[5,48,97,48,5,10,97,10],"nuv":[0.04672897196261682,0.1724137931034483,0.9065420560747663,0.1724137931034483,0.04672897196261682,0.8275862068965517,0.9065420560747663,0.8275862068965517],"minPos":{"x":-46,"y":-19,"z":0},"maxPos":{"x":46,"y":19,"z":0}},"packable":true,"pixelsToUnit":100,"pivot":{"x":0.5,"y":0.5},"meshType":0}],[0],0,[0],[0],[0]]
