[1,0,0,[["cc.JsonAsset",["_name","json"],1]],[[0,0,1,3]],[[0,"motion",{"frameRate":12,"die":{"frames":[{"res":"z_108","x":313,"y":323}]},"hit":{"frames":[{"res":"z_109","x":304,"y":258}]},"attack":{"frames":[{"res":"z_104","x":251,"y":214},{"res":"z_103","x":251,"y":223},{"res":"z_102","x":251,"y":224},{"res":"z_101","x":251,"y":224},{"res":"z_106","x":251,"y":224},{"res":"z_105","x":251,"y":224},{"res":"z_107","x":307,"y":243},{"res":"z_110","x":306,"y":263}]},"stand":{"frames":[{"res":"z_201","x":306,"y":260},{"res":"z_204","x":305,"y":257},{"res":"z_203","x":305,"y":252},{"res":"z_202","x":306,"y":250},{"res":"z_208","x":306,"y":243},{"res":"z_207","x":306,"y":249},{"res":"z_206","x":305,"y":255},{"res":"z_205","x":305,"y":255}]}}]],0,0,[],[],[]]
